{
  "company_name": "Synthomer",
  "sanitized_name": "Synthomer",
  "company_type": "product-driven",
  "type_name": "产品驱动型",
  "origin_type": "foreign",
  "origin_name": "外国公司",
  "first_analysis_date": "2026-01-20",
  "last_analysis_date": "2026-01-21 04:45:00",
  "analysis_count": 1,
  "cache_version": "v2.2.0",
  "output_files": {
    "json_report": "outputs/RevGrowth_Synthomer.json",
    "markdown_report": "outputs/RevGrowth_FullReport_Synthomer.md"
  },
  "key_results": {
    "score": 1.3,
    "rating": "不推荐",
    "cagr": 2.1,
    "current_revenue": 1.9,
    "forecast_revenue_2031": 2.19
  },
  "dimension_cache_status": {
    "公司基础信息": {
      "last_updated": "2026-01-21 04:45:00",
      "cache_status": "fresh",
      "source_count": 3,
      "file_size": 0
    },
    "双曲线业务分析": {
      "last_updated": "2026-01-21 04:45:00",
      "cache_status": "fresh",
      "source_count": 3,
      "file_size": 0
    },
    "行业与市场分析": {
      "last_updated": "2026-01-21 04:45:00",
      "cache_status": "fresh",
      "source_count": 3,
      "file_size": 0
    },
    "竞争格局分析": {
      "last_updated": "2026-01-21 04:45:00",
      "cache_status": "fresh",
      "source_count": 2,
      "file_size": 0
    },
    "产能与扩张分析": {
      "last_updated": "2026-01-21 04:45:00",
      "cache_status": "fresh",
      "source_count": 2,
      "file_size": 0
    },
    "技术与创新分析": {
      "last_updated": "2026-01-21 04:45:00",
      "cache_status": "fresh",
      "source_count": 2,
      "file_size": 0
    },
    "宏观政策分析": {
      "last_updated": "2026-01-21 04:45:00",
      "cache_status": "fresh",
      "source_count": 2,
      "file_size": 0
    },
    "客户与渠道分析": {
      "last_updated": "2026-01-21 04:45:00",
      "cache_status": "fresh",
      "source_count": 2,
      "file_size": 0
    },
    "需求端分析": {
      "last_updated": "2026-01-21 04:45:00",
      "cache_status": "fresh",
      "source_count": 2,
      "file_size": 0
    }
  },
  "search_keywords_history": {
    "公司基础信息": [
      "Synthomer latest financial report 2024 2025 revenue EBITDA",
      "Synthomer business segments revenue structure by division",
      "Synthomer annual report 2024 2025 strategic transformation"
    ],
    "双曲线业务分析": [
      "Synthomer traditional business core business",
      "Synthomer new business strategic transformation",
      "Synthomer revenue structure change business transformation"
    ],
    "行业与市场分析": [
      "specialty chemicals polymers market size growth forecast",
      "synthetic polymers market CAGR future trends",
      "emulsion polymer market AI impact digitalization"
    ],
    "竞争格局分析": [
      "Synthomer competitors market share",
      "Synthomer vs BASF Dow Arkema comparison",
      "specialty chemicals market concentration competitive landscape"
    ],
    "产能与扩张分析": [
      "Synthomer capacity expansion plan new facilities",
      "Synthomer manufacturing sites production capacity"
    ],
    "技术与创新分析": [
      "Synthomer R&D investment new products innovation",
      "Synthomer patents technology breakthrough sustainability"
    ],
    "宏观政策分析": [
      "chemicals industry policy support regulation 2025",
      "specialty chemicals environmental regulations REACH compliance"
    ],
    "客户与渠道分析": [
      "Synthomer key customers contracts major accounts",
      "Synthomer international expansion global markets"
    ],
    "需求端分析": [
      "specialty chemicals downstream demand structure applications",
      "construction coatings adhesives market growth drivers"
    ]
  },
  "search_results_count": 21,
  "analysis_summary": "Synthomer面临严重财务困境,高杠杆(5.25x)和现金流紧张,综合CAGR仅2.1%,评级为不推荐(1.3/10分)"
}